pysubnet/__init__.py
pysubnet/accounts.py
pysubnet/chainspec.py
pysubnet/chainspec_handlers.py
pysubnet/cli.py
pysubnet/ethereum.py
pysubnet/main.py
pysubnet/helpers/__init__.py
pysubnet/helpers/config.py
pysubnet/helpers/process.py
pysubnet/helpers/prompts.py
pysubnet/helpers/substrate.py
pysubnet-2.2.1.dist-info/METADATA
pysubnet-2.2.1.dist-info/WHEEL
pysubnet-2.2.1.dist-info/entry_points.txt
pysubnet-2.2.1.dist-info/licenses/LICENSE
pysubnet-2.2.1.dist-info/RECORD
