Metadata-Version: 2.4
Name: pysubnet
Version: 2.2.1
Summary: Deploy a substrate permissioned network using python
Project-URL: homepage, https://github.com/weezy20/pysubnet
Project-URL: repository, https://github.com/weezy20/pysubnet
Author-email: Abhishek Shah <abhishekshah3@gmail.com>
License-Expression: Apache-2.0
License-File: LICENSE
Classifier: Development Status :: 5 - Production/Stable
Classifier: Intended Audience :: Developers
Classifier: License :: OSI Approved :: Apache Software License
Classifier: Operating System :: OS Independent
Classifier: Programming Language :: Python :: 3.10
Classifier: Programming Language :: Python :: 3.11
Classifier: Programming Language :: Python :: 3.12
Classifier: Programming Language :: Python :: 3.13
Classifier: Topic :: Software Development :: Build Tools
Classifier: Topic :: Software Development :: Testing
Classifier: Topic :: System :: Distributed Computing
Classifier: Topic :: System :: Networking
Requires-Python: >=3.10
Requires-Dist: docker>=7.1.0
Requires-Dist: eth-hash[pysha3]>=0.7.1
Requires-Dist: eth-keys>=0.7.0
Requires-Dist: eth-utils>=5.2.0
Requires-Dist: pydantic>=2.11.3
Requires-Dist: rich>=14.0.0
Requires-Dist: tomli>=2.2.1
